git_client-1.0.1.dist-info/licenses/LICENSE
gitclient/__init__.py
gitclient/ignore.py
gitclient/main.py
git_client-1.0.1.dist-info/METADATA
git_client-1.0.1.dist-info/WHEEL
git_client-1.0.1.dist-info/entry_points.txt
git_client-1.0.1.dist-info/top_level.txt
git_client-1.0.1.dist-info/RECORD
