Metadata-Version: 2.4
Name: git-client
Version: 1.0.1
Summary: gc is a command line helper client for using git.
Home-page: https://gitlab.com/shindagger/git-client
Author: Andy Klier
Author-email: andyklier@gmail.com
License: MIT
Classifier: Programming Language :: Python :: 3
Classifier: Operating System :: OS Independent
License-File: LICENSE
Requires-Dist: setuptools
Requires-Dist: inquirer
Requires-Dist: string-color>=0.2.7
Dynamic: author
Dynamic: author-email
Dynamic: classifier
Dynamic: description
Dynamic: description-content-type
Dynamic: home-page
Dynamic: license
Dynamic: license-file
Dynamic: requires-dist
Dynamic: summary
